pyumlify/__init__.py
pyumlify/__main__.py
pyumlify/cli.py
pyumlify/generate.py
pyumlify-0.1.1.dist-info/licenses/LICENSE
pyumlify-0.1.1.dist-info/METADATA
pyumlify-0.1.1.dist-info/WHEEL
pyumlify-0.1.1.dist-info/entry_points.txt
pyumlify-0.1.1.dist-info/top_level.txt
pyumlify-0.1.1.dist-info/RECORD
