Metadata-Version: 2.4
Name: pyumlify
Version: 0.1.1
Summary: Generate PlantUML diagrams from Python code automatically.
Author-email: Guilherme Ditzel Patriota <gdp.ai.data.eng@gmail.com>
License: GPL-3.0-or-later
Keywords: plantuml,uml,python,diagrams,code generation,automation
Requires-Python: >=3.8
License-File: LICENSE
Requires-Dist: stdlib_list
Dynamic: license-file
